example/__init__.py
example/models.py
nebula_model/__init__.py
nebula_model/settings.py
nebula_model/models/__init__.py
nebula_model/models/abstract.py
nebula_model/models/errors.py
nebula_model/models/fields.py
nebula_model/models/managers.py
nebula_model/models/migrations.py
nebula_model/models/model_builder.py
nebula_model/models/models.py
nebula_model/models/query/__init__.py
nebula_model/ngql/__init__.py
nebula_model/ngql/errors.py
nebula_model/ngql/connection/__init__.py
nebula_model/ngql/connection/connection.py
nebula_model/ngql/query/__init__.py
nebula_model/ngql/query/conditions.py
nebula_model/ngql/query/match.py
nebula_model/ngql/record/__init__.py
nebula_model/ngql/record/edge.py
nebula_model/ngql/record/vertex.py
nebula_model/ngql/schema/__init__.py
nebula_model/ngql/schema/data_types.py
nebula_model/ngql/schema/schema.py
nebula_model/ngql/schema/space.py
nebula_model/ngql/statements/__init__.py
nebula_model/ngql/statements/clauses.py
nebula_model/ngql/statements/core.py
nebula_model/ngql/statements/edge.py
nebula_model/ngql/statements/schema.py
nebula_model/utils/__init__.py
nebula_model/utils/utils.py
tests/__init__.py
tests/base.py
tests/test_ngql_record.py
tests/test_ngql_schema.py
tests/test_ngql_space.py
nebula_model-0.1.0.dist-info/LICENSE
nebula_model-0.1.0.dist-info/METADATA
nebula_model-0.1.0.dist-info/WHEEL
nebula_model-0.1.0.dist-info/top_level.txt
nebula_model-0.1.0.dist-info/RECORD
